{
    "type": "bundle",
    "id": "bundle--f916681a-cb23-489a-91d0-6650b901337e",
    "spec_version": "2.0",
    "objects": [
        {
            "type": "attack-pattern",
            "id": "attack-pattern--62b8c999-dcc0-4755-bd69-09442d9359f5",
            "created_by_ref": "identity--c78cb6e5-0c4b-4611-8297-d1b8b55e40b5",
            "created": "2017-05-31T21:31:06.045Z",
            "modified": "2017-12-14T16:55:59.600Z",
            "name": "Rundll32",
            "description": "The rundll32.exe program can be called to execute an arbitrary binary. Adversaries may take advantage of this functionality to proxy execution of code to avoid triggering security tools that may not monitor execution of the rundll32.exe process because of whitelists or false positives from Windows using rundll32.exe for normal operations.\n\nDetection: Use process monitoring to monitor the execution and arguments of rundll32.exe. Compare recent invocations of rundll32.exe with prior history of known good arguments and loaded DLLs to determine anomalous and potentially adversarial activity. Command arguments used with the rundll32.exe invocation may also be useful in determining the origin and purpose of the DLL being loaded.\n\nPlatforms: Windows Server 2003, Windows Server 2008, Windows Server 2012, Windows XP, Windows 7, Windows 8, Windows Server 2003 R2, Windows Server 2008 R2, Windows Server 2012 R2, Windows Vista, Windows 8.1, Windows 10\n\nData Sources: File monitoring, Binary file metadata, Process command-line parameters, Process monitoring\n\nDefense Bypassed: Anti-virus, Application whitelisting\n\nPermissions Required: User\n\nRemote Support: No",
            "kill_chain_phases": [
                {
                    "kill_chain_name": "mitre-attack",
                    "phase_name": "defense-evasion"
                },
                {
                    "kill_chain_name": "mitre-attack",
                    "phase_name": "execution"
                }
            ],
            "external_references": [
                {
                    "source_name": "mitre-attack",
                    "url": "https://attack.mitre.org/wiki/Technique/T1085",
                    "external_id": "T1085"
                }
            ],
            "object_marking_refs": [
                "marking-definition--fa42a846-8d90-4e51-bc29-71d5b4802168"
            ],
            "x_mitre_data_sources": [
                "File monitoring",
                "Binary file metadata",
                "Process command-line parameters",
                "Process monitoring"
            ],
            "x_mitre_defense_bypassed": [
                "Anti-virus",
                "Application whitelisting"
            ],
            "x_mitre_permissions_required": [
                "User"
            ],
            "x_mitre_platforms": [
                "Windows Server 2003",
                "Windows Server 2008",
                "Windows Server 2012",
                "Windows XP",
                "Windows 7",
                "Windows 8",
                "Windows Server 2003 R2",
                "Windows Server 2008 R2",
                "Windows Server 2012 R2",
                "Windows Vista",
                "Windows 8.1",
                "Windows 10"
            ],
            "x_mitre_remote_support": false
        }
    ]
}